sensorkit/pwi4/__init__.py
sensorkit_pwi4-0.1.0.dist-info/METADATA
sensorkit_pwi4-0.1.0.dist-info/WHEEL
sensorkit_pwi4-0.1.0.dist-info/RECORD
