Metadata-Version: 2.4
Name: sensorkit-pwi4
Version: 0.1.0
Summary: PlaneWave PWI4 utilities for SensorKit.
Author: Ryan Swindle
License: MIT
Classifier: License :: OSI Approved :: MIT License
Classifier: Operating System :: OS Independent
Classifier: Programming Language :: Python :: 3
Requires-Python: >=3.13
